minifiedstorage
