Metadata-Version: 1.1
Name: django-minifiedstorage
Version: 0.3
Summary: Simple minified storage for django static assets
Home-page: http://github.com/askholme/django_minifiedstorage
Author: Ask Holme
Author-email: ask@askholme.dk
License: BSD
Keywords: django staticfiles static assets production minify compress
Platform: UNKNOWN
Classifier: Development Status :: 4 - Beta
Classifier: License :: OSI Approved :: BSD License
Classifier: Programming Language :: Python :: 2.7
Classifier: Framework :: Django
Classifier: Topic :: Internet :: WWW/HTTP
